{
  "_class": "shapePath",
  "booleanOperation": -1,
  "do_objectID": "70A62F5C-0E83-4426-83DA-2D4C785D78A6",
  "edited": true,
  "exportOptions": {
    "_class": "exportOptions",
    "do_objectID": "B9A857C7-7CC2-44B1-8D11-1CB1D214F8F3",
    "exportFormats": [
    ],
    "includedLayerIds": [
    ],
    "layerOptions": 0,
    "shouldTrim": false
  },
  "frame": {
    "_class": "rect",
    "constrainProportions": false,
    "do_objectID": "79C8BCA5-05B8-4467-B6CB-EA97D01C6A6B",
    "height": 0.5,
    "width": 304,
    "x": 0,
    "y": 0
  },
  "isClosed": false,
  "isFixedToViewport": false,
  "isFlippedHorizontal": false,
  "isFlippedVertical": false,
  "isLocked": false,
  "isVisible": true,
  "layerListExpandedType": 0,
  "name": "Path",
  "nameIsFixed": false,
  "pointRadiusBehaviour": 1,
  "points": [
    {
      "_class": "curvePoint",
      "cornerRadius": 0,
      "curveFrom": "{0.0032894736842105257, 0.66666666666666663}",
      "curveMode": 1,
      "curveTo": "{0.0032894736842105257, 0.66666666666666663}",
      "hasCurveFrom": false,
      "hasCurveTo": false,
      "point": "{0.0016447368421052628, 0.5}"
    },
    {
      "_class": "curvePoint",
      "cornerRadius": 0,
      "curveFrom": "{0.0065789473684210514, 1}",
      "curveMode": 1,
      "curveTo": "{0.0065789473684210514, 1}",
      "hasCurveFrom": false,
      "hasCurveTo": false,
      "point": "{0.99835526315789469, 0.5}"
    }
  ],
  "resizingConstraint": 63,
  "resizingType": 0,
  "rotation": 0,
  "shouldBreakMaskChain": false
}