{
  "_class": "text",
  "attributedString": {
    "_class": "attributedString",
    "attributes": [
      {
        "_class": "stringAttribute",
        "attributes": {
          "MSAttributedStringColorAttribute": {
            "_class": "color",
            "alpha": 1,
            "blue": 0.07058823529411765,
            "green": 0.07058823529411765,
            "red": 0.07058823529411765
          },
          "MSAttributedStringFontAttribute": {
            "_class": "fontDescriptor",
            "attributes": {
              "name": "OpenSans-Regular",
              "size": 14
            }
          },
          "kerning": 0,
          "paragraphStyle": {
            "_class": "paragraphStyle",
            "alignment": 0,
            "allowsDefaultTighteningForTruncation": 0,
            "maximumLineHeight": 16,
            "minimumLineHeight": 16
          },
          "textStyleVerticalAlignmentKey": 1
        },
        "length": 6,
        "location": 0
      }
    ],
    "string": "Grupos"
  },
  "automaticallyDrawOnUnderlyingPath": false,
  "booleanOperation": -1,
  "do_objectID": "AA824FE7-0050-4B60-B63E-3657F8C56D3F",
  "dontSynchroniseWithSymbol": false,
  "exportOptions": {
    "_class": "exportOptions",
    "do_objectID": "7CAFD2F8-FE10-4A7C-843B-71F971C7AF4C",
    "exportFormats": [
    ],
    "includedLayerIds": [
    ],
    "layerOptions": 0,
    "shouldTrim": false
  },
  "frame": {
    "_class": "rect",
    "constrainProportions": false,
    "do_objectID": "8BEF7F25-02AB-41C4-89FF-97C446DFEDC1",
    "height": 16,
    "width": 49,
    "x": 154,
    "y": 157
  },
  "glyphBounds": "{{0, 2}, {48, 15}}",
  "isFixedToViewport": false,
  "isFlippedHorizontal": false,
  "isFlippedVertical": false,
  "isLocked": false,
  "isVisible": true,
  "layerListExpandedType": 0,
  "lineSpacingBehaviour": 2,
  "name": "Grupos",
  "nameIsFixed": false,
  "resizingConstraint": 47,
  "resizingType": 0,
  "rotation": 0,
  "shouldBreakMaskChain": false,
  "style": {
    "_class": "style",
    "do_objectID": "7199DE24-98F6-4934-B988-824BA1065B8A",
    "endMarkerType": 0,
    "miterLimit": 10,
    "startMarkerType": 0,
    "textStyle": {
      "_class": "textStyle",
      "do_objectID": "9698FF34-9F79-4082-B198-05C704B174A0",
      "encodedAttributes": {
        "MSAttributedStringColorAttribute": {
          "_class": "color",
          "alpha": 1,
          "blue": 0.07058823529411765,
          "green": 0.07058823529411765,
          "red": 0.07058823529411765
        },
        "MSAttributedStringFontAttribute": {
          "_class": "fontDescriptor",
          "attributes": {
            "name": "OpenSans-Regular",
            "size": 14
          }
        },
        "kerning": 0,
        "paragraphStyle": {
          "_class": "paragraphStyle",
          "alignment": 0,
          "allowsDefaultTighteningForTruncation": 0,
          "maximumLineHeight": 16,
          "minimumLineHeight": 16
        },
        "textStyleVerticalAlignmentKey": 1
      },
      "verticalAlignment": 1
    },
    "windingRule": 1
  },
  "textBehaviour": 0
}